<?xml version="1.0" encoding="utf-8" ?>
<dwsync>
<file name="command1.htm" server="ftp.hollyforks.com///" local="130600656000000000" remote="130600656000000000" />
<file name="ducommnd.htm" server="ftp.hollyforks.com///" local="130600656000000000" remote="130600656000000000" />
<file name="es_gibt.htm" server="ftp.hollyforks.com///" local="130600656000000000" remote="130600656000000000" />
<file name="haben.htm" server="ftp.hollyforks.com///" local="130600656000000000" remote="130600656000000000" />
<file name="ihrcommn.htm" server="ftp.hollyforks.com///" local="130600656000000000" remote="130600656000000000" />
<file name="lassen.htm" server="ftp.hollyforks.com///" local="130600656000000000" remote="130600656000000000" />
<file name="modlform.htm" server="ftp.hollyforks.com///" local="130600656000000000" remote="130600656000000000" />
<file name="modlfunc.htm" server="ftp.hollyforks.com///" local="130600656000000000" remote="130600656000000000" />
<file name="presmean.htm" server="ftp.hollyforks.com///" local="130600656000000000" remote="130600656000000000" />
<file name="reflverb.htm" server="ftp.hollyforks.com///" local="130600656000000000" remote="130600656000000000" />
<file name="regverbs.htm" server="ftp.hollyforks.com///" local="130600656000000000" remote="130600656000000000" />
<file name="sein.htm" server="ftp.hollyforks.com///" local="130600656000000000" remote="130600656000000000" />
<file name="sepprefx.htm" server="ftp.hollyforks.com///" local="130600656000000000" remote="130600656000000000" />
<file name="siecommn.htm" server="ftp.hollyforks.com///" local="130600656000000000" remote="130600656000000000" />
<file name="to_like.htm" server="ftp.hollyforks.com///" local="130600656000000000" remote="130600656000000000" />
<file name="tontlike.htm" server="ftp.hollyforks.com///" local="130600656000000000" remote="130600656000000000" />
<file name="vbsspobj.htm" server="ftp.hollyforks.com///" local="130600656000000000" remote="130600656000000000" />
<file name="verbssz.htm" server="ftp.hollyforks.com///" local="130600656000000000" remote="130600656000000000" />
<file name="verbstd.htm" server="ftp.hollyforks.com///" local="130600656000000000" remote="130600656000000000" />
<file name="verbstem.htm" server="ftp.hollyforks.com///" local="130600656000000000" remote="130600656000000000" />
<file name="werden.htm" server="ftp.hollyforks.com///" local="130600656000000000" remote="130600656000000000" />
<file name="woodlike.htm" server="ftp.hollyforks.com///" local="130600656000000000" remote="130600656000000000" />
<file name="command1.htm" server="50.87.140.189/public_html/" local="133270282060265087" remote="133286311270000000" />
<file name="ducommnd.htm" server="50.87.140.189/public_html/" local="133270282056790081" remote="133286311270000000" />
<file name="es_gibt.htm" server="50.87.140.189/public_html/" local="133270282057311458" remote="133286311280000000" />
<file name="haben.htm" server="50.87.140.189/public_html/" local="133270282057591353" remote="133286311280000000" />
<file name="ihrcommn.htm" server="50.87.140.189/public_html/" local="133230608834952261" remote="133286311280000000" />
<file name="lassen.htm" server="50.87.140.189/public_html/" local="133270282057941219" remote="133286311280000000" />
<file name="modlform.htm" server="50.87.140.189/public_html/" local="133256102414031095" remote="133286311290000000" />
<file name="modlfunc.htm" server="50.87.140.189/public_html/" local="133270282058166183" remote="133286311290000000" />
<file name="presmean.htm" server="50.87.140.189/public_html/" local="133270282058445782" remote="133286311290000000" />
<file name="reflverb.htm" server="50.87.140.189/public_html/" local="133270282059075549" remote="133286311290000000" />
<file name="regverbs.htm" server="50.87.140.189/public_html/" local="133270282061524647" remote="133286311300000000" />
<file name="sein.htm" server="50.87.140.189/public_html/" local="133270282059285461" remote="133286311300000000" />
<file name="sepprefx.htm" server="50.87.140.189/public_html/" local="133270282060125167" remote="133286311300000000" />
<file name="siecommn.htm" server="50.87.140.189/public_html/" local="133230608835600537" remote="133286311310000000" />
<file name="tontlike.htm" server="50.87.140.189/public_html/" local="133230608836089234" remote="133286311310000000" />
<file name="to_like.htm" server="50.87.140.189/public_html/" local="133270282062907794" remote="133286311310000000" />
<file name="vbsspobj.htm" server="50.87.140.189/public_html/" local="133258081445396061" remote="133286311310000000" />
<file name="verbssz.htm" server="50.87.140.189/public_html/" local="133270282061244718" remote="133286311320000000" />
<file name="verbstd.htm" server="50.87.140.189/public_html/" local="133239075345781974" remote="133286311320000000" />
<file name="verbstem.htm" server="50.87.140.189/public_html/" local="133270282062487672" remote="133286311320000000" />
<file name="werden.htm" server="50.87.140.189/public_html/" local="133270282063202078" remote="133286311320000000" />
<file name="woodlike.htm" server="50.87.140.189/public_html/" local="133230608836468521" remote="133286311320000000" />
<file name="siecommn- backup.htm" server="50.87.140.189/public_html/" local="133236260256490753" remote="133286311300000000" />
<file name="regverbs.htm" server="ftp.hollyforks.com//public_html/" local="133374464351327620" remote="133374392400000000" />
<file name="regverbs.htm" server="ftp.hollyforks.com/public_html/" local="133413561147702788" remote="133413489000000000" />
<file name="to_like.htm" server="ftp.hollyforks.com/public_html/" local="133419764648757839" remote="133419692400000000" />
<file name="modlfunc.htm" server="ftp.hollyforks.com/public_html/" local="133425470908813157" remote="133425398400000000" />
</dwsync>